{"response": {"termsofService": "http://www.wunderground.com/weather/api/d/terms.html", "version": "0.1", "features": {"history": 1}}, "history": {"date": {"mday": "27", "hour": "00", "min": "00", "mon": "02", "pretty": "February 27, 2018", "year": "2018", "tzname": "America/Vancouver"}, "utcdate": {"mday": "27", "hour": "08", "min": "00", "mon": "02", "pretty": "February 27, 2018", "year": "2018", "tzname": "UTC"}, "observations": [{"heatindexm": "-9999", "windchillm": "-999", "wdire": "NE", "wdird": "42", "windchilli": "-999", "heatindexi": "-9999", "solarradiation": "", "pressurei": "30.11", "pressurem": "1019.5", "hum": "97", "tempi": "37.6", "tempm": "3.1", "dewptm": "2.7", "dewpti": "36.8", "date": {"mday": "27", "hour": "00", "min": "01", "mon": "02", "pretty": "12:01 AM PST on February 27, 2018", "year": "2018", "tzname": "America/Vancouver"}, "precip_totalm": "0.0", "softwaretype": "WeatherDisplay:10.37", "utcdate": {"mday": "27", "hour": "08", "min": "01", "mon": "02", "pretty": "8:01 AM GMT on February 27, 2018", "year": "2018", "tzname": "UTC"}, "precip_ratem": "0.0", "precip_ratei": "0.00", "precip_totali": "0.00", "UV": "", "wgusti": "0.0", "wgustm": "0.0", "wspdi": "1.1", "wspdm": "1.8"}, {"heatindexm": "-9999", "windchillm": "1.7", "wdire": "ESE", "wdird": "114", "windchilli": "35.1", "heatindexi": "-9999", "solarradiation": "", "pressurei": "30.10", "pressurem": "1019.2", "hum": "97", "tempi": "37.6", "tempm": "3.1", "dewptm": "2.7", "dewpti": "36.8", "date": {"mday": "27", "hour": "00", "min": "06", "mon": "02", "pretty": "12:06 AM PST on February 27, 2018", "year": "2018", "tzname": "America/Vancouver"}, "precip_totalm": "0.0", "softwaretype": "WeatherDisplay:10.37", "utcdate": {"mday": "27", "hour": "08", "min": "06", "mon": "02", "pretty": "8:06 AM GMT on February 27, 2018", "year": "2018", "tzname": "UTC"}, "precip_ratem": "0.0", "precip_ratei": "0.00", "precip_totali": "0.00", "UV": "", "wgusti": "3.5", "wgustm": "5.6", "wspdi": "3.5", "wspdm": "5.6"}, {"heatindexm": "-9999", "windchillm": "-999", "wdire": "ESE", "wdird": "116", "windchilli": "-999", "heatindexi": "-9999", "solarradiation": "", "pressurei": "30.10", "pressurem": "1019.2", "hum": "97", "tempi": "37.5", "tempm": "3.1", "dewptm": "2.6", "dewpti": "36.7", "date": {"mday": "27", "hour": "00", "min": "11", "mon": "02", "pretty": "12:11 AM PST on February 27, 2018", "year": "2018", "tzname": "America/Vancouver"}, "precip_totalm": "0.0", "softwaretype": "WeatherDisplay:10.37", "utcdate": {"mday": "27", "hour": "08", "min": "11", "mon": "02", "pretty": "8:11 AM GMT on February 27, 2018", "year": "2018", "tzname": "UTC"}, "precip_ratem": "0.0", "precip_ratei": "0.00", "precip_totali": "0.00", "UV": "", "wgusti": "0.0", "wgustm": "0.0", "wspdi": "0.0", "wspdm": "0.0"}, {"heatindexm": "-9999", "windchillm": "1.6", "wdire": "ESE", "wdird": "120", "windchilli": "35.0", "heatindexi": "-9999", "solarradiation": "", "pressurei": "30.10", "pressurem": "1019.2", "hum": "97", "tempi": "37.5", "tempm": "3.1", "dewptm": "2.6", "dewpti": "36.7", "date": {"mday": "27", "hour": "00", "min": "16", "mon": "02", "pretty": "12:16 AM PST on February 27, 2018", "year": "2018", "tzname": "America/Vancouver"}, "precip_totalm": "0.0", "softwaretype": "WeatherDisplay:10.37", "utcdate": {"mday": "27", "hour": "08", "min": "16", "mon": "02", "pretty": "8:16 AM GMT on February 27, 2018", "year": "2018", "tzname": "UTC"}, "precip_ratem": "0.0", "precip_ratei": "0.00", "precip_totali": "0.00", "UV": "", "wgusti": "3.5", "wgustm": "5.6", "wspdi": "3.5", "wspdm": "5.6"}, {"heatindexm": "-9999", "windchillm": "1.4", "wdire": "ESE", "wdird": "112", "windchilli": "34.4", "heatindexi": "-9999", "solarradiation": "", "pressurei": "30.10", "pressurem": "1019.2", "hum": "97", "tempi": "37.5", "tempm": "3.1", "dewptm": "2.6", "dewpti": "36.7", "date": {"mday": "27", "hour": "00", "min": "21", "mon": "02", "pretty": "12:21 AM PST on February 27, 2018", "year": "2018", "tzname": "America/Vancouver"}, "precip_totalm": "0.0", "softwaretype": "WeatherDisplay:10.37", "utcdate": {"mday": "27", "hour": "08", "min": "21", "mon": "02", "pretty": "8:21 AM GMT on February 27, 2018", "year": "2018", "tzname": "UTC"}, "precip_ratem": "0.0", "precip_ratei": "0.00", "precip_totali": "0.00", "UV": "", "wgusti": "4.0", "wgustm": "6.4", "wspdi": "4.0", "wspdm": "6.4"}, {"heatindexm": "-9999", "windchillm": "0.9", "wdire": "ESE", "wdird": "113", "windchilli": "33.5", "heatindexi": "-9999", "solarradiation": "", "pressurei": "30.10", "pressurem": "1019.2", "hum": "97", "tempi": "37.5", "tempm": "3.1", "dewptm": "2.6", "dewpti": "36.7", "date": {"mday": "27", "hour": "00", "min": "26", "mon": "02", "pretty": "12:26 AM PST on February 27, 2018", "year": "2018", "tzname": "America/Vancouver"}, "precip_totalm": "0.0", "softwaretype": "WeatherDisplay:10.37", "utcdate": {"mday": "27", "hour": "08", "min": "26", "mon": "02", "pretty": "8:26 AM GMT on February 27, 2018", "year": "2018", "tzname": "UTC"}, "precip_ratem": "0.0", "precip_ratei": "0.00", "precip_totali": "0.00", "UV": "", "wgusti": "5.0", "wgustm": "8.0", "wspdi": "5.0", "wspdm": "8.0"}, {"heatindexm": "-9999", "windchillm": "-999", "wdire": "ESE", "wdird": "112", "windchilli": "-999", "heatindexi": "-9999", "solarradiation": "", "pressurei": "30.10", "pressurem": "1019.2", "hum": "97", "tempi": "37.4", "tempm": "3.0", "dewptm": "2.6", "dewpti": "36.6", "date": {"mday": "27", "hour": "00", "min": "31", "mon": "02", "pretty": "12:31 AM PST on February 27, 2018", "year": "2018", "tzname": "America/Vancouver"}, "precip_totalm": "0.0", "softwaretype": "WeatherDisplay:10.37", "utcdate": {"mday": "27", "hour": "08", "min": "31", "mon": "02", "pretty": "8:31 AM GMT on February 27, 2018", "year": "2018", "tzname": "UTC"}, "precip_ratem": "0.0", "precip_ratei": "0.00", "precip_totali": "0.00", "UV": "", "wgusti": "3.0", "wgustm": "4.8", "wspdi": "3.0", "wspdm": "4.8"}, {"heatindexm": "-9999", "windchillm": "-999", "wdire": "ESE", "wdird": "114", "windchilli": "-999", "heatindexi": "-9999", "solarradiation": "", "pressurei": "30.10", "pressurem": "1019.2", "hum": "97", "tempi": "37.3", "tempm": "2.9", "dewptm": "2.5", "dewpti": "36.5", "date": {"mday": "27", "hour": "00", "min": "36", "mon": "02", "pretty": "12:36 AM PST on February 27, 2018", "year": "2018", "tzname": "America/Vancouver"}, "precip_totalm": "0.0", "softwaretype": "WeatherDisplay:10.37", "utcdate": {"mday": "27", "hour": "08", "min": "36", "mon": "02", "pretty": "8:36 AM GMT on February 27, 2018", "year": "2018", "tzname": "UTC"}, "precip_ratem": "0.0", "precip_ratei": "0.00", "precip_totali": "0.00", "UV": "", "wgusti": "0.0", "wgustm": "0.0", "wspdi": "0.0", "wspdm": "0.0"}, {"heatindexm": "-9999", "windchillm": "-999", "wdire": "ESE", "wdird": "113", "windchilli": "-999", "heatindexi": "-9999", "solarradiation": "", "pressurei": "30.10", "pressurem": "1019.2", "hum": "99", "tempi": "37.4", "tempm": "3.0", "dewptm": "2.8", "dewpti": "37.1", "date": {"mday": "27", "hour": "00", "min": "41", "mon": "02", "pretty": "12:41 AM PST on February 27, 2018", "year": "2018", "tzname": "America/Vancouver"}, "precip_totalm": "0.0", "softwaretype": "WeatherDisplay:10.37", "utcdate": {"mday": "27", "hour": "08", "min": "41", "mon": "02", "pretty": "8:41 AM GMT on February 27, 2018", "year": "2018", "tzname": "UTC"}, "precip_ratem": "0.0", "precip_ratei": "0.00", "precip_totali": "0.00", "UV": "", "wgusti": "0.0", "wgustm": "0.0", "wspdi": "0.0", "wspdm": "0.0"}, {"heatindexm": "-9999", "windchillm": "-999", "wdire": "ESE", "wdird": "114", "windchilli": "-999", "heatindexi": "-9999", "solarradiation": "", "pressurei": "30.10", "pressurem": "1019.2", "hum": "99", "tempi": "37.5", "tempm": "3.1", "dewptm": "2.9", "dewpti": "37.2", "date": {"mday": "27", "hour": "00", "min": "46", "mon": "02", "pretty": "12:46 AM PST on February 27, 2018", "year": "2018", "tzname": "America/Vancouver"}, "precip_totalm": "0.3", "softwaretype": "WeatherDisplay:10.37", "utcdate": {"mday": "27", "hour": "08", "min": "46", "mon": "02", "pretty": "8:46 AM GMT on February 27, 2018", "year": "2018", "tzname": "UTC"}, "precip_ratem": "0.3", "precip_ratei": "0.01", "precip_totali": "0.01", "UV": "", "wgusti": "0.0", "wgustm": "0.0", "wspdi": "0.0", "wspdm": "0.0"}, {"heatindexm": "-9999", "windchillm": "-999", "wdire": "ESE", "wdird": "114", "windchilli": "-999", "heatindexi": "-9999", "solarradiation": "", "pressurei": "30.10", "pressurem": "1019.2", "hum": "100", "tempi": "37.7", "tempm": "3.2", "dewptm": "3.2", "dewpti": "37.7", "date": {"mday": "27", "hour": "00", "min": "51", "mon": "02", "pretty": "12:51 AM PST on February 27, 2018", "year": "2018", "tzname": "America/Vancouver"}, "precip_totalm": "0.3", "softwaretype": "WeatherDisplay:10.37", "utcdate": {"mday": "27", "hour": "08", "min": "51", "mon": "02", "pretty": "8:51 AM GMT on February 27, 2018", "year": "2018", "tzname": "UTC"}, "precip_ratem": "0.3", "precip_ratei": "0.01", "precip_totali": "0.01", "UV": "", "wgusti": "0.0", "wgustm": "0.0", "wspdi": "0.0", "wspdm": "0.0"}, {"heatindexm": "-9999", "windchillm": "1.8", "wdire": "ESE", "wdird": "114", "windchilli": "35.3", "heatindexi": "-9999", "solarradiation": "", "pressurei": "30.10", "pressurem": "1019.2", "hum": "100", "tempi": "37.8", "tempm": "3.2", "dewptm": "3.2", "dewpti": "37.8", "date": {"mday": "27", "hour": "00", "min": "56", "mon": "02", "pretty": "12:56 AM PST on February 27, 2018", "year": "2018", "tzname": "America/Vancouver"}, "precip_totalm": "0.3", "softwaretype": "WeatherDisplay:10.37", "utcdate": {"mday": "27", "hour": "08", "min": "56", "mon": "02", "pretty": "8:56 AM GMT on February 27, 2018", "year": "2018", "tzname": "UTC"}, "precip_ratem": "0.3", "precip_ratei": "0.01", "precip_totali": "0.01", "UV": "", "wgusti": "3.5", "wgustm": "5.6", "wspdi": "3.5", "wspdm": "5.6"}, {"heatindexm": "-9999", "windchillm": "-999", "wdire": "ESE", "wdird": "114", "windchilli": "-999", "heatindexi": "-9999", "solarradiation": "", "pressurei": "30.10", "pressurem": "1019.2", "hum": "100", "tempi": "37.8", "tempm": "3.2", "dewptm": "3.2", "dewpti": "37.8", "date": {"mday": "27", "hour": "01", "min": "01", "mon": "02", "pretty": "1:01 AM PST on February 27, 2018", "year": "2018", "tzname": "America/Vancouver"}, "precip_totalm": "0.3", "softwaretype": "WeatherDisplay:10.37", "utcdate": {"mday": "27", "hour": "09", "min": "01", "mon": "02", "pretty": "9:01 AM GMT on February 27, 2018", "year": "2018", "tzname": "UTC"}, "precip_ratem": "0.3", "precip_ratei": "0.01", "precip_totali": "0.01", "UV": "", "wgusti": "0.0", "wgustm": "0.0", "wspdi": "0.0", "wspdm": "0.0"}, {"heatindexm": "-9999", "windchillm": "-999", "wdire": "ESE", "wdird": "114", "windchilli": "-999", "heatindexi": "-9999", "solarradiation": "", "pressurei": "30.10", "pressurem": "1019.2", "hum": "99", "tempi": "37.9", "tempm": "3.3", "dewptm": "3.1", "dewpti": "37.6", "date": {"mday": "27", "hour": "01", "min": "06", "mon": "02", "pretty": "1:06 AM PST on February 27, 2018", "year": "2018", "tzname": "America/Vancouver"}, "precip_totalm": "0.3", "softwaretype": "WeatherDisplay:10.37", "utcdate": {"mday": "27", "hour": "09", "min": "06", "mon": "02", "pretty": "9:06 AM GMT on February 27, 2018", "year": "2018", "tzname": "UTC"}, "precip_ratem": "0.3", "precip_ratei": "0.01", "precip_totali": "0.01", "UV": "", "wgusti": "0.0", "wgustm": "0.0", "wspdi": "0.0", "wspdm": "0.0"}, {"heatindexm": "-9999", "windchillm": "1.8", "wdire": "ESE", "wdird": "114", "windchilli": "35.3", "heatindexi": "-9999", "solarradiation": "", "pressurei": "30.10", "pressurem": "1019.2", "hum": "99", "tempi": "37.8", "tempm": "3.2", "dewptm": "3.1", "dewpti": "37.5", "date": {"mday": "27", "hour": "01", "min": "11", "mon": "02", "pretty": "1:11 AM PST on February 27, 2018", "year": "2018", "tzname": "America/Vancouver"}, "precip_totalm": "0.3", "softwaretype": "WeatherDisplay:10.37", "utcdate": {"mday": "27", "hour": "09", "min": "11", "mon": "02", "pretty": "9:11 AM GMT on February 27, 2018", "year": "2018", "tzname": "UTC"}, "precip_ratem": "0.3", "precip_ratei": "0.01", "precip_totali": "0.01", "UV": "", "wgusti": "3.5", "wgustm": "5.6", "wspdi": "3.5", "wspdm": "5.6"}, {"heatindexm": "-9999", "windchillm": "-999", "wdire": "ESE", "wdird": "114", "windchilli": "-999", "heatindexi": "-9999", "solarradiation": "", "pressurei": "30.10", "pressurem": "1019.2", "hum": "99", "tempi": "37.8", "tempm": "3.2", "dewptm": "3.1", "dewpti": "37.5", "date": {"mday": "27", "hour": "01", "min": "16", "mon": "02", "pretty": "1:16 AM PST on February 27, 2018", "year": "2018", "tzname": "America/Vancouver"}, "precip_totalm": "0.3", "softwaretype": "WeatherDisplay:10.37", "utcdate": {"mday": "27", "hour": "09", "min": "16", "mon": "02", "pretty": "9:16 AM GMT on February 27, 2018", "year": "2018", "tzname": "UTC"}, "precip_ratem": "0.3", "precip_ratei": "0.01", "precip_totali": "0.01", "UV": "", "wgusti": "0.0", "wgustm": "0.0", "wspdi": "0.0", "wspdm": "0.0"}, {"heatindexm": "-9999", "windchillm": "1.2", "wdire": "ESE", "wdird": "115", "windchilli": "34.1", "heatindexi": "-9999", "solarradiation": "", "pressurei": "30.10", "pressurem": "1019.2", "hum": "98", "tempi": "37.7", "tempm": "3.2", "dewptm": "2.9", "dewpti": "37.2", "date": {"mday": "27", "hour": "01", "min": "21", "mon": "02", "pretty": "1:21 AM PST on February 27, 2018", "year": "2018", "tzname": "America/Vancouver"}, "precip_totalm": "0.3", "softwaretype": "WeatherDisplay:10.37", "utcdate": {"mday": "27", "hour": "09", "min": "21", "mon": "02", "pretty": "9:21 AM GMT on February 27, 2018", "year": "2018", "tzname": "UTC"}, "precip_ratem": "0.3", "precip_ratei": "0.01", "precip_totali": "0.01", "UV": "", "wgusti": "4.6", "wgustm": "7.4", "wspdi": "4.6", "wspdm": "7.4"}, {"heatindexm": "-9999", "windchillm": "-999", "wdire": "ESE", "wdird": "115", "windchilli": "-999", "heatindexi": "-9999", "solarradiation": "", "pressurei": "30.10", "pressurem": "1019.2", "hum": "98", "tempi": "37.7", "tempm": "3.2", "dewptm": "2.9", "dewpti": "37.2", "date": {"mday": "27", "hour": "01", "min": "26", "mon": "02", "pretty": "1:26 AM PST on February 27, 2018", "year": "2018", "tzname": "America/Vancouver"}, "precip_totalm": "0.3", "softwaretype": "WeatherDisplay:10.37", "utcdate": {"mday": "27", "hour": "09", "min": "26", "mon": "02", "pretty": "9:26 AM GMT on February 27, 2018", "year": "2018", "tzname": "UTC"}, "precip_ratem": "0.3", "precip_ratei": "0.01", "precip_totali": "0.01", "UV": "", "wgusti": "0.0", "wgustm": "0.0", "wspdi": "0.0", "wspdm": "0.0"}, {"heatindexm": "-9999", "windchillm": "1.0", "wdire": "ESE", "wdird": "116", "windchilli": "33.8", "heatindexi": "-9999", "solarradiation": "", "pressurei": "30.10", "pressurem": "1019.2", "hum": "98", "tempi": "37.7", "tempm": "3.2", "dewptm": "2.9", "dewpti": "37.2", "date": {"mday": "27", "hour": "01", "min": "31", "mon": "02", "pretty": "1:31 AM PST on February 27, 2018", "year": "2018", "tzname": "America/Vancouver"}, "precip_totalm": "0.3", "softwaretype": "WeatherDisplay:10.37", "utcdate": {"mday": "27", "hour": "09", "min": "31", "mon": "02", "pretty": "9:31 AM GMT on February 27, 2018", "year": "2018", "tzname": "UTC"}, "precip_ratem": "0.3", "precip_ratei": "0.01", "precip_totali": "0.01", "UV": "", "wgusti": "5.0", "wgustm": "8.0", "wspdi": "5.0", "wspdm": "8.0"}, {"heatindexm": "-9999", "windchillm": "1.8", "wdire": "ESE", "wdird": "117", "windchilli": "35.2", "heatindexi": "-9999", "solarradiation": "", "pressurei": "30.10", "pressurem": "1019.2", "hum": "98", "tempi": "37.7", "tempm": "3.2", "dewptm": "2.9", "dewpti": "37.2", "date": {"mday": "27", "hour": "01", "min": "36", "mon": "02", "pretty": "1:36 AM PST on February 27, 2018", "year": "2018", "tzname": "America/Vancouver"}, "precip_totalm": "0.3", "softwaretype": "WeatherDisplay:10.37", "utcdate": {"mday": "27", "hour": "09", "min": "36", "mon": "02", "pretty": "9:36 AM GMT on February 27, 2018", "year": "2018", "tzname": "UTC"}, "precip_ratem": "0.3", "precip_ratei": "0.01", "precip_totali": "0.01", "UV": "", "wgusti": "0.0", "wgustm": "0.0", "wspdi": "3.5", "wspdm": "5.6"}, {"heatindexm": "-9999", "windchillm": "1.8", "wdire": "ESE", "wdird": "117", "windchilli": "35.3", "heatindexi": "-9999", "solarradiation": "", "pressurei": "30.10", "pressurem": "1019.2", "hum": "99", "tempi": "37.8", "tempm": "3.2", "dewptm": "3.1", "dewpti": "37.5", "date": {"mday": "27", "hour": "01", "min": "41", "mon": "02", "pretty": "1:41 AM PST on February 27, 2018", "year": "2018", "tzname": "America/Vancouver"}, "precip_totalm": "0.3", "softwaretype": "WeatherDisplay:10.37", "utcdate": {"mday": "27", "hour": "09", "min": "41", "mon": "02", "pretty": "9:41 AM GMT on February 27, 2018", "year": "2018", "tzname": "UTC"}, "precip_ratem": "0.3", "precip_ratei": "0.01", "precip_totali": "0.01", "UV": "", "wgusti": "3.5", "wgustm": "5.6", "wspdi": "3.5", "wspdm": "5.6"}, {"heatindexm": "-9999", "windchillm": "0.7", "wdire": "ESE", "wdird": "120", "windchilli": "33.3", "heatindexi": "-9999", "solarradiation": "", "pressurei": "30.10", "pressurem": "1019.2", "hum": "98", "tempi": "37.8", "tempm": "3.2", "dewptm": "2.9", "dewpti": "37.3", "date": {"mday": "27", "hour": "01", "min": "47", "mon": "02", "pretty": "1:47 AM PST on February 27, 2018", "year": "2018", "tzname": "America/Vancouver"}, "precip_totalm": "0.3", "softwaretype": "WeatherDisplay:10.37", "utcdate": {"mday": "27", "hour": "09", "min": "47", "mon": "02", "pretty": "9:47 AM GMT on February 27, 2018", "year": "2018", "tzname": "UTC"}, "precip_ratem": "0.0", "precip_ratei": "0.00", "precip_totali": "0.01", "UV": "", "wgusti": "0.0", "wgustm": "0.0", "wspdi": "5.8", "wspdm": "9.3"}, {"heatindexm": "-9999", "windchillm": "-999", "wdire": "ESE", "wdird": "120", "windchilli": "-999", "heatindexi": "-9999", "solarradiation": "", "pressurei": "30.10", "pressurem": "1019.2", "hum": "99", "tempi": "37.9", "tempm": "3.3", "dewptm": "3.1", "dewpti": "37.6", "date": {"mday": "27", "hour": "01", "min": "52", "mon": "02", "pretty": "1:52 AM PST on February 27, 2018", "year": "2018", "tzname": "America/Vancouver"}, "precip_totalm": "0.3", "softwaretype": "WeatherDisplay:10.37", "utcdate": {"mday": "27", "hour": "09", "min": "52", "mon": "02", "pretty": "9:52 AM GMT on February 27, 2018", "year": "2018", "tzname": "UTC"}, "precip_ratem": "0.0", "precip_ratei": "0.00", "precip_totali": "0.01", "UV": "", "wgusti": "2.0", "wgustm": "3.2", "wspdi": "2.0", "wspdm": "3.2"}, {"heatindexm": "-9999", "windchillm": "-999", "wdire": "ESE", "wdird": "120", "windchilli": "-999", "heatindexi": "-9999", "solarradiation": "", "pressurei": "30.10", "pressurem": "1019.2", "hum": "98", "tempi": "37.9", "tempm": "3.3", "dewptm": "3.0", "dewpti": "37.4", "date": {"mday": "27", "hour": "01", "min": "57", "mon": "02", "pretty": "1:57 AM PST on February 27, 2018", "year": "2018", "tzname": "America/Vancouver"}, "precip_totalm": "0.3", "softwaretype": "WeatherDisplay:10.37", "utcdate": {"mday": "27", "hour": "09", "min": "57", "mon": "02", "pretty": "9:57 AM GMT on February 27, 2018", "year": "2018", "tzname": "UTC"}, "precip_ratem": "0.0", "precip_ratei": "0.00", "precip_totali": "0.01", "UV": "", "wgusti": "0.0", "wgustm": "0.0", "wspdi": "0.0", "wspdm": "0.0"}, {"heatindexm": "-9999", "windchillm": "2.0", "wdire": "ESE", "wdird": "120", "windchilli": "35.6", "heatindexi": "-9999", "solarradiation": "", "pressurei": "30.10", "pressurem": "1019.2", "hum": "99", "tempi": "38.1", "tempm": "3.4", "dewptm": "3.2", "dewpti": "37.8", "date": {"mday": "27", "hour": "02", "min": "02", "mon": "02", "pretty": "2:02 AM PST on February 27, 2018", "year": "2018", "tzname": "America/Vancouver"}, "precip_totalm": "0.3", "softwaretype": "WeatherDisplay:10.37", "utcdate": {"mday": "27", "hour": "10", "min": "02", "mon": "02", "pretty": "10:02 AM GMT on February 27, 2018", "year": "2018", "tzname": "UTC"}, "precip_ratem": "0.0", "precip_ratei": "0.00", "precip_totali": "0.01", "UV": "", "wgusti": "3.5", "wgustm": "5.6", "wspdi": "3.5", "wspdm": "5.6"}, {"heatindexm": "-9999", "windchillm": "2.0", "wdire": "ESE", "wdird": "120", "windchilli": "35.6", "heatindexi": "-9999", "solarradiation": "", "pressurei": "30.10", "pressurem": "1019.2", "hum": "98", "tempi": "38.1", "tempm": "3.4", "dewptm": "3.1", "dewpti": "37.6", "date": {"mday": "27", "hour": "02", "min": "07", "mon": "02", "pretty": "2:07 AM PST on February 27, 2018", "year": "2018", "tzname": "America/Vancouver"}, "precip_totalm": "0.3", "softwaretype": "WeatherDisplay:10.37", "utcdate": {"mday": "27", "hour": "10", "min": "07", "mon": "02", "pretty": "10:07 AM GMT on February 27, 2018", "year": "2018", "tzname": "UTC"}, "precip_ratem": "0.0", "precip_ratei": "0.00", "precip_totali": "0.01", "UV": "", "wgusti": "0.0", "wgustm": "0.0", "wspdi": "3.5", "wspdm": "5.6"}, {"heatindexm": "-9999", "windchillm": "2.1", "wdire": "ESE", "wdird": "120", "windchilli": "35.8", "heatindexi": "-9999", "solarradiation": "", "pressurei": "30.10", "pressurem": "1019.2", "hum": "98", "tempi": "38.2", "tempm": "3.4", "dewptm": "3.2", "dewpti": "37.7", "date": {"mday": "27", "hour": "02", "min": "12", "mon": "02", "pretty": "2:12 AM PST on February 27, 2018", "year": "2018", "tzname": "America/Vancouver"}, "precip_totalm": "0.3", "softwaretype": "WeatherDisplay:10.37", "utcdate": {"mday": "27", "hour": "10", "min": "12", "mon": "02", "pretty": "10:12 AM GMT on February 27, 2018", "year": "2018", "tzname": "UTC"}, "precip_ratem": "0.0", "precip_ratei": "0.00", "precip_totali": "0.01", "UV": "", "wgusti": "3.5", "wgustm": "5.6", "wspdi": "3.5", "wspdm": "5.6"}, {"heatindexm": "-9999", "windchillm": "-999", "wdire": "ESE", "wdird": "120", "windchilli": "-999", "heatindexi": "-9999", "solarradiation": "", "pressurei": "30.10", "pressurem": "1019.2", "hum": "98", "tempi": "38.2", "tempm": "3.4", "dewptm": "3.2", "dewpti": "37.7", "date": {"mday": "27", "hour": "02", "min": "17", "mon": "02", "pretty": "2:17 AM PST on February 27, 2018", "year": "2018", "tzname": "America/Vancouver"}, "precip_totalm": "0.3", "softwaretype": "WeatherDisplay:10.37", "utcdate": {"mday": "27", "hour": "10", "min": "17", "mon": "02", "pretty": "10:17 AM GMT on February 27, 2018", "year": "2018", "tzname": "UTC"}, "precip_ratem": "0.0", "precip_ratei": "0.00", "precip_totali": "0.01", "UV": "", "wgusti": "2.3", "wgustm": "3.7", "wspdi": "2.3", "wspdm": "3.7"}, {"heatindexm": "-9999", "windchillm": "-999", "wdire": "ESE", "wdird": "120", "windchilli": "-999", "heatindexi": "-9999", "solarradiation": "", "pressurei": "30.11", "pressurem": "1019.5", "hum": "98", "tempi": "38.3", "tempm": "3.5", "dewptm": "3.2", "dewpti": "37.8", "date": {"mday": "27", "hour": "02", "min": "22", "mon": "02", "pretty": "2:22 AM PST on February 27, 2018", "year": "2018", "tzname": "America/Vancouver"}, "precip_totalm": "0.3", "softwaretype": "WeatherDisplay:10.37", "utcdate": {"mday": "27", "hour": "10", "min": "22", "mon": "02", "pretty": "10:22 AM GMT on February 27, 2018", "year": "2018", "tzname": "UTC"}, "precip_ratem": "0.0", "precip_ratei": "0.00", "precip_totali": "0.01", "UV": "", "wgusti": "0.0", "wgustm": "0.0", "wspdi": "0.0", "wspdm": "0.0"}, {"heatindexm": "-9999", "windchillm": "2.2", "wdire": "ESE", "wdird": "120", "windchilli": "36.0", "heatindexi": "-9999", "solarradiation": "", "pressurei": "30.11", "pressurem": "1019.5", "hum": "98", "tempi": "38.4", "tempm": "3.6", "dewptm": "3.3", "dewpti": "37.9", "date": {"mday": "27", "hour": "02", "min": "27", "mon": "02", "pretty": "2:27 AM PST on February 27, 2018", "year": "2018", "tzname": "America/Vancouver"}, "precip_totalm": "0.3", "softwaretype": "WeatherDisplay:10.37", "utcdate": {"mday": "27", "hour": "10", "min": "27", "mon": "02", "pretty": "10:27 AM GMT on February 27, 2018", "year": "2018", "tzname": "UTC"}, "precip_ratem": "0.0", "precip_ratei": "0.00", "precip_totali": "0.01", "UV": "", "wgusti": "3.5", "wgustm": "5.6", "wspdi": "3.5", "wspdm": "5.6"}, {"heatindexm": "-9999", "windchillm": "-999", "wdire": "ESE", "wdird": "120", "windchilli": "-999", "heatindexi": "-9999", "solarradiation": "", "pressurei": "30.10", "pressurem": "1019.2", "hum": "98", "tempi": "38.4", "tempm": "3.6", "dewptm": "3.3", "dewpti": "37.9", "date": {"mday": "27", "hour": "02", "min": "32", "mon": "02", "pretty": "2:32 AM PST on February 27, 2018", "year": "2018", "tzname": "America/Vancouver"}, "precip_totalm": "0.3", "softwaretype": "WeatherDisplay:10.37", "utcdate": {"mday": "27", "hour": "10", "min": "32", "mon": "02", "pretty": "10:32 AM GMT on February 27, 2018", "year": "2018", "tzname": "UTC"}, "precip_ratem": "0.0", "precip_ratei": "0.00", "precip_totali": "0.01", "UV": "", "wgusti": "2.3", "wgustm": "3.7", "wspdi": "2.3", "wspdm": "3.7"}, {"heatindexm": "-9999", "windchillm": "-999", "wdire": "ESE", "wdird": "121", "windchilli": "-999", "heatindexi": "-9999", "solarradiation": "", "pressurei": "30.10", "pressurem": "1019.2", "hum": "98", "tempi": "38.4", "tempm": "3.6", "dewptm": "3.3", "dewpti": "37.9", "date": {"mday": "27", "hour": "02", "min": "37", "mon": "02", "pretty": "2:37 AM PST on February 27, 2018", "year": "2018", "tzname": "America/Vancouver"}, "precip_totalm": "0.3", "softwaretype": "WeatherDisplay:10.37", "utcdate": {"mday": "27", "hour": "10", "min": "37", "mon": "02", "pretty": "10:37 AM GMT on February 27, 2018", "year": "2018", "tzname": "UTC"}, "precip_ratem": "0.0", "precip_ratei": "0.00", "precip_totali": "0.01", "UV": "", "wgusti": "0.0", "wgustm": "0.0", "wspdi": "0.0", "wspdm": "0.0"}, {"heatindexm": "-9999", "windchillm": "-999", "wdire": "ESE", "wdird": "121", "windchilli": "-999", "heatindexi": "-9999", "solarradiation": "", "pressurei": "30.09", "pressurem": "1018.8", "hum": "98", "tempi": "38.5", "tempm": "3.6", "dewptm": "3.3", "dewpti": "38.0", "date": {"mday": "27", "hour": "02", "min": "42", "mon": "02", "pretty": "2:42 AM PST on February 27, 2018", "year": "2018", "tzname": "America/Vancouver"}, "precip_totalm": "0.3", "softwaretype": "WeatherDisplay:10.37", "utcdate": {"mday": "27", "hour": "10", "min": "42", "mon": "02", "pretty": "10:42 AM GMT on February 27, 2018", "year": "2018", "tzname": "UTC"}, "precip_ratem": "0.0", "precip_ratei": "0.00", "precip_totali": "0.01", "UV": "", "wgusti": "0.0", "wgustm": "0.0", "wspdi": "0.0", "wspdm": "0.0"}, {"heatindexm": "-9999", "windchillm": "-999", "wdire": "ESE", "wdird": "120", "windchilli": "-999", "heatindexi": "-9999", "solarradiation": "", "pressurei": "30.09", "pressurem": "1018.8", "hum": "98", "tempi": "38.4", "tempm": "3.6", "dewptm": "3.3", "dewpti": "37.9", "date": {"mday": "27", "hour": "02", "min": "47", "mon": "02", "pretty": "2:47 AM PST on February 27, 2018", "year": "2018", "tzname": "America/Vancouver"}, "precip_totalm": "0.3", "softwaretype": "WeatherDisplay:10.37", "utcdate": {"mday": "27", "hour": "10", "min": "47", "mon": "02", "pretty": "10:47 AM GMT on February 27, 2018", "year": "2018", "tzname": "UTC"}, "precip_ratem": "0.0", "precip_ratei": "0.00", "precip_totali": "0.01", "UV": "", "wgusti": "0.0", "wgustm": "0.0", "wspdi": "0.0", "wspdm": "0.0"}, {"heatindexm": "-9999", "windchillm": "-999", "wdire": "ESE", "wdird": "120", "windchilli": "-999", "heatindexi": "-9999", "solarradiation": "", "pressurei": "30.09", "pressurem": "1018.8", "hum": "97", "tempi": "38.4", "tempm": "3.6", "dewptm": "3.1", "dewpti": "37.6", "date": {"mday": "27", "hour": "02", "min": "52", "mon": "02", "pretty": "2:52 AM PST on February 27, 2018", "year": "2018", "tzname": "America/Vancouver"}, "precip_totalm": "0.3", "softwaretype": "WeatherDisplay:10.37", "utcdate": {"mday": "27", "hour": "10", "min": "52", "mon": "02", "pretty": "10:52 AM GMT on February 27, 2018", "year": "2018", "tzname": "UTC"}, "precip_ratem": "0.0", "precip_ratei": "0.00", "precip_totali": "0.01", "UV": "", "wgusti": "0.0", "wgustm": "0.0", "wspdi": "0.0", "wspdm": "0.0"}, {"heatindexm": "-9999", "windchillm": "1.6", "wdire": "ESE", "wdird": "120", "windchilli": "34.8", "heatindexi": "-9999", "solarradiation": "", "pressurei": "30.09", "pressurem": "1018.8", "hum": "97", "tempi": "38.3", "tempm": "3.5", "dewptm": "3.1", "dewpti": "37.5", "date": {"mday": "27", "hour": "02", "min": "57", "mon": "02", "pretty": "2:57 AM PST on February 27, 2018", "year": "2018", "tzname": "America/Vancouver"}, "precip_totalm": "0.3", "softwaretype": "WeatherDisplay:10.37", "utcdate": {"mday": "27", "hour": "10", "min": "57", "mon": "02", "pretty": "10:57 AM GMT on February 27, 2018", "year": "2018", "tzname": "UTC"}, "precip_ratem": "0.0", "precip_ratei": "0.00", "precip_totali": "0.01", "UV": "", "wgusti": "4.6", "wgustm": "7.4", "wspdi": "4.6", "wspdm": "7.4"}, {"heatindexm": "-9999", "windchillm": "1.6", "wdire": "ESE", "wdird": "119", "windchilli": "34.8", "heatindexi": "-9999", "solarradiation": "", "pressurei": "30.09", "pressurem": "1018.8", "hum": "97", "tempi": "38.3", "tempm": "3.5", "dewptm": "3.1", "dewpti": "37.5", "date": {"mday": "27", "hour": "03", "min": "02", "mon": "02", "pretty": "3:02 AM PST on February 27, 2018", "year": "2018", "tzname": "America/Vancouver"}, "precip_totalm": "0.3", "softwaretype": "WeatherDisplay:10.37", "utcdate": {"mday": "27", "hour": "11", "min": "02", "mon": "02", "pretty": "11:02 AM GMT on February 27, 2018", "year": "2018", "tzname": "UTC"}, "precip_ratem": "0.0", "precip_ratei": "0.00", "precip_totali": "0.01", "UV": "", "wgusti": "4.6", "wgustm": "7.4", "wspdi": "4.6", "wspdm": "7.4"}, {"heatindexm": "-9999", "windchillm": "2.1", "wdire": "ESE", "wdird": "116", "windchilli": "35.8", "heatindexi": "-9999", "solarradiation": "", "pressurei": "30.09", "pressurem": "1018.8", "hum": "97", "tempi": "38.2", "tempm": "3.4", "dewptm": "3.0", "dewpti": "37.4", "date": {"mday": "27", "hour": "03", "min": "07", "mon": "02", "pretty": "3:07 AM PST on February 27, 2018", "year": "2018", "tzname": "America/Vancouver"}, "precip_totalm": "0.3", "softwaretype": "WeatherDisplay:10.37", "utcdate": {"mday": "27", "hour": "11", "min": "07", "mon": "02", "pretty": "11:07 AM GMT on February 27, 2018", "year": "2018", "tzname": "UTC"}, "precip_ratem": "0.0", "precip_ratei": "0.00", "precip_totali": "0.01", "UV": "", "wgusti": "3.5", "wgustm": "5.6", "wspdi": "3.5", "wspdm": "5.6"}, {"heatindexm": "-9999", "windchillm": "0.2", "wdire": "ESE", "wdird": "122", "windchilli": "32.4", "heatindexi": "-9999", "solarradiation": "", "pressurei": "30.09", "pressurem": "1018.8", "hum": "97", "tempi": "38.2", "tempm": "3.4", "dewptm": "3.0", "dewpti": "37.4", "date": {"mday": "27", "hour": "03", "min": "12", "mon": "02", "pretty": "3:12 AM PST on February 27, 2018", "year": "2018", "tzname": "America/Vancouver"}, "precip_totalm": "0.3", "softwaretype": "WeatherDisplay:10.37", "utcdate": {"mday": "27", "hour": "11", "min": "12", "mon": "02", "pretty": "11:12 AM GMT on February 27, 2018", "year": "2018", "tzname": "UTC"}, "precip_ratem": "0.0", "precip_ratei": "0.00", "precip_totali": "0.01", "UV": "", "wgusti": "8.1", "wgustm": "13.0", "wspdi": "8.1", "wspdm": "13.0"}, {"heatindexm": "-9999", "windchillm": "1.5", "wdire": "ESE", "wdird": "122", "windchilli": "34.7", "heatindexi": "-9999", "solarradiation": "", "pressurei": "30.08", "pressurem": "1018.5", "hum": "97", "tempi": "38.2", "tempm": "3.4", "dewptm": "3.0", "dewpti": "37.4", "date": {"mday": "27", "hour": "03", "min": "17", "mon": "02", "pretty": "3:17 AM PST on February 27, 2018", "year": "2018", "tzname": "America/Vancouver"}, "precip_totalm": "0.3", "softwaretype": "WeatherDisplay:10.37", "utcdate": {"mday": "27", "hour": "11", "min": "17", "mon": "02", "pretty": "11:17 AM GMT on February 27, 2018", "year": "2018", "tzname": "UTC"}, "precip_ratem": "0.0", "precip_ratei": "0.00", "precip_totali": "0.01", "UV": "", "wgusti": "4.6", "wgustm": "7.4", "wspdi": "4.6", "wspdm": "7.4"}, {"heatindexm": "-9999", "windchillm": "1.5", "wdire": "ESE", "wdird": "122", "windchilli": "34.7", "heatindexi": "-9999", "solarradiation": "", "pressurei": "30.08", "pressurem": "1018.5", "hum": "97", "tempi": "38.2", "tempm": "3.4", "dewptm": "3.0", "dewpti": "37.4", "date": {"mday": "27", "hour": "03", "min": "22", "mon": "02", "pretty": "3:22 AM PST on February 27, 2018", "year": "2018", "tzname": "America/Vancouver"}, "precip_totalm": "0.3", "softwaretype": "WeatherDisplay:10.37", "utcdate": {"mday": "27", "hour": "11", "min": "22", "mon": "02", "pretty": "11:22 AM GMT on February 27, 2018", "year": "2018", "tzname": "UTC"}, "precip_ratem": "0.0", "precip_ratei": "0.00", "precip_totali": "0.01", "UV": "", "wgusti": "4.6", "wgustm": "7.4", "wspdi": "4.6", "wspdm": "7.4"}, {"heatindexm": "-9999", "windchillm": "1.0", "wdire": "ESE", "wdird": "123", "windchilli": "33.8", "heatindexi": "-9999", "solarradiation": "", "pressurei": "30.08", "pressurem": "1018.5", "hum": "97", "tempi": "38.2", "tempm": "3.4", "dewptm": "3.0", "dewpti": "37.4", "date": {"mday": "27", "hour": "03", "min": "27", "mon": "02", "pretty": "3:27 AM PST on February 27, 2018", "year": "2018", "tzname": "America/Vancouver"}, "precip_totalm": "0.3", "softwaretype": "WeatherDisplay:10.37", "utcdate": {"mday": "27", "hour": "11", "min": "27", "mon": "02", "pretty": "11:27 AM GMT on February 27, 2018", "year": "2018", "tzname": "UTC"}, "precip_ratem": "0.0", "precip_ratei": "0.00", "precip_totali": "0.01", "UV": "", "wgusti": "5.8", "wgustm": "9.3", "wspdi": "5.8", "wspdm": "9.3"}, {"heatindexm": "-9999", "windchillm": "1.8", "wdire": "SE", "wdird": "125", "windchilli": "35.3", "heatindexi": "-9999", "solarradiation": "", "pressurei": "30.07", "pressurem": "1018.2", "hum": "98", "tempi": "38.2", "tempm": "3.4", "dewptm": "3.2", "dewpti": "37.7", "date": {"mday": "27", "hour": "03", "min": "32", "mon": "02", "pretty": "3:32 AM PST on February 27, 2018", "year": "2018", "tzname": "America/Vancouver"}, "precip_totalm": "0.3", "softwaretype": "WeatherDisplay:10.37", "utcdate": {"mday": "27", "hour": "11", "min": "32", "mon": "02", "pretty": "11:32 AM GMT on February 27, 2018", "year": "2018", "tzname": "UTC"}, "precip_ratem": "0.0", "precip_ratei": "0.00", "precip_totali": "0.01", "UV": "", "wgusti": "4.0", "wgustm": "6.4", "wspdi": "4.0", "wspdm": "6.4"}, {"heatindexm": "-9999", "windchillm": "2.2", "wdire": "SE", "wdird": "125", "windchilli": "35.9", "heatindexi": "-9999", "solarradiation": "", "pressurei": "30.08", "pressurem": "1018.5", "hum": "98", "tempi": "38.3", "tempm": "3.5", "dewptm": "3.2", "dewpti": "37.8", "date": {"mday": "27", "hour": "03", "min": "37", "mon": "02", "pretty": "3:37 AM PST on February 27, 2018", "year": "2018", "tzname": "America/Vancouver"}, "precip_totalm": "0.3", "softwaretype": "WeatherDisplay:10.37", "utcdate": {"mday": "27", "hour": "11", "min": "37", "mon": "02", "pretty": "11:37 AM GMT on February 27, 2018", "year": "2018", "tzname": "UTC"}, "precip_ratem": "0.0", "precip_ratei": "0.00", "precip_totali": "0.01", "UV": "", "wgusti": "3.5", "wgustm": "5.6", "wspdi": "3.5", "wspdm": "5.6"}, {"heatindexm": "-9999", "windchillm": "0.6", "wdire": "SE", "wdird": "126", "windchilli": "33.2", "heatindexi": "-9999", "solarradiation": "", "pressurei": "30.07", "pressurem": "1018.2", "hum": "98", "tempi": "38.3", "tempm": "3.5", "dewptm": "3.2", "dewpti": "37.8", "date": {"mday": "27", "hour": "03", "min": "42", "mon": "02", "pretty": "3:42 AM PST on February 27, 2018", "year": "2018", "tzname": "America/Vancouver"}, "precip_totalm": "0.3", "softwaretype": "WeatherDisplay:10.37", "utcdate": {"mday": "27", "hour": "11", "min": "42", "mon": "02", "pretty": "11:42 AM GMT on February 27, 2018", "year": "2018", "tzname": "UTC"}, "precip_ratem": "0.0", "precip_ratei": "0.00", "precip_totali": "0.01", "UV": "", "wgusti": "6.9", "wgustm": "11.1", "wspdi": "6.9", "wspdm": "11.1"}, {"heatindexm": "-9999", "windchillm": "1.6", "wdire": "SE", "wdird": "127", "windchilli": "34.8", "heatindexi": "-9999", "solarradiation": "", "pressurei": "30.07", "pressurem": "1018.2", "hum": "98", "tempi": "38.3", "tempm": "3.5", "dewptm": "3.2", "dewpti": "37.8", "date": {"mday": "27", "hour": "03", "min": "47", "mon": "02", "pretty": "3:47 AM PST on February 27, 2018", "year": "2018", "tzname": "America/Vancouver"}, "precip_totalm": "0.3", "softwaretype": "WeatherDisplay:10.37", "utcdate": {"mday": "27", "hour": "11", "min": "47", "mon": "02", "pretty": "11:47 AM GMT on February 27, 2018", "year": "2018", "tzname": "UTC"}, "precip_ratem": "0.0", "precip_ratei": "0.00", "precip_totali": "0.01", "UV": "", "wgusti": "4.6", "wgustm": "7.4", "wspdi": "4.6", "wspdm": "7.4"}, {"heatindexm": "-9999", "windchillm": "2.2", "wdire": "SE", "wdird": "127", "windchilli": "36.0", "heatindexi": "-9999", "solarradiation": "", "pressurei": "30.07", "pressurem": "1018.2", "hum": "99", "tempi": "38.4", "tempm": "3.6", "dewptm": "3.4", "dewpti": "38.1", "date": {"mday": "27", "hour": "03", "min": "52", "mon": "02", "pretty": "3:52 AM PST on February 27, 2018", "year": "2018", "tzname": "America/Vancouver"}, "precip_totalm": "0.3", "softwaretype": "WeatherDisplay:10.37", "utcdate": {"mday": "27", "hour": "11", "min": "52", "mon": "02", "pretty": "11:52 AM GMT on February 27, 2018", "year": "2018", "tzname": "UTC"}, "precip_ratem": "0.0", "precip_ratei": "0.00", "precip_totali": "0.01", "UV": "", "wgusti": "3.5", "wgustm": "5.6", "wspdi": "3.5", "wspdm": "5.6"}, {"heatindexm": "-9999", "windchillm": "2.3", "wdire": "SE", "wdird": "127", "windchilli": "36.1", "heatindexi": "-9999", "solarradiation": "", "pressurei": "30.07", "pressurem": "1018.2", "hum": "99", "tempi": "38.5", "tempm": "3.6", "dewptm": "3.4", "dewpti": "38.2", "date": {"mday": "27", "hour": "03", "min": "57", "mon": "02", "pretty": "3:57 AM PST on February 27, 2018", "year": "2018", "tzname": "America/Vancouver"}, "precip_totalm": "0.3", "softwaretype": "WeatherDisplay:10.37", "utcdate": {"mday": "27", "hour": "11", "min": "57", "mon": "02", "pretty": "11:57 AM GMT on February 27, 2018", "year": "2018", "tzname": "UTC"}, "precip_ratem": "0.0", "precip_ratei": "0.00", "precip_totali": "0.01", "UV": "", "wgusti": "0.0", "wgustm": "0.0", "wspdi": "3.5", "wspdm": "5.6"}], "dailysummary": [{"maxpressurem": "1019.5", "maxdewptm": "3.4", "maxpressurei": "30.11", "maxdewpti": "38.2", "maxwspdm": "13.0", "mindewptm": "2.5", "maxwspdi": "8.1", "meanwindspdi": "2.7", "meanwindspdm": "4.4", "meandewptm": "3.0", "mindewpti": "36.5", "mintempi": "37.3", "meandewpti": "37.4", "mintempm": "2.9", "minhumidity": "97", "meanwdird": "", "meanwdire": "ESE", "date": {"mday": "27", "hour": "00", "min": "00", "mon": "02", "pretty": "February 27, 2018", "year": "2018", "tzname": "America/Vancouver"}, "utcdate": {"mday": "27", "hour": "08", "min": "00", "mon": "02", "pretty": "February 27, 2018", "year": "2018", "tzname": "UTC"}, "maxhumidity": "100", "maxtempm": "3.6", "minpressurei": "30.07", "maxtempi": "38.5", "minpressurem": "1018.2", "humidity": "98", "precipi": "0.01", "precipm": "0.3", "meantempi": "37.9", "meantempm": "3.3"}]}}