{"datetime_utc": "2016-02-12 18:05:37.685931 UTC", "data": [{"mintempi": 38, "dayname": "Mon", "maxtempi": 50, "daynum": 1, "precipi": 0.08, "precipi_is_zero": false}, {"mintempi": 39, "dayname": "Tue", "maxtempi": 47, "daynum": 2, "precipi": 0.07, "precipi_is_zero": false}, {"mintempi": 43, "dayname": "Wed", "maxtempi": 48, "daynum": 3, "precipi": 0.6, "precipi_is_zero": false}, {"mintempi": 46, "dayname": "Thu", "maxtempi": 52, "daynum": 4, "precipi": 0.55, "precipi_is_zero": false}, {"mintempi": 47, "dayname": "Fri", "maxtempi": 56, "daynum": 5, "precipi": 0.16, "precipi_is_zero": false}, {"mintempi": 43, "dayname": "Sat", "maxtempi": 52, "daynum": 6, "precipi": 0.01, "precipi_is_zero": false}, {"mintempi": 43, "dayname": "Sun", "maxtempi": 59, "daynum": 7, "precipi": 0.0, "precipi_is_zero": true}, {"mintempi": 45, "dayname": "Mon", "maxtempi": 61, "daynum": 8, "precipi": 0.0, "precipi_is_zero": true}, {"mintempi": 51, "dayname": "Tue", "maxtempi": 66, "daynum": 9, "precipi": 0.0, "precipi_is_zero": true}, {"mintempi": 48, "dayname": "Wed", "maxtempi": 55, "daynum": 10, "precipi": 0.13, "precipi_is_zero": false}, {"mintempi": 49, "dayname": "Thu", "maxtempi": 57, "daynum": 11, "precipi": 0.63, "precipi_is_zero": false}, {"mintempi": 48, "dayname": "Sat", "maxtempi": 51, "daynum": 13, "precipi": 100, "precipi_is_zero": false, "is_forecast": true}, {"mintempi": 49, "dayname": "Sun", "maxtempi": 53, "daynum": 14, "precipi": 90, "precipi_is_zero": false, "is_forecast": true}, {"mintempi": 48, "dayname": "Mon", "maxtempi": 55, "daynum": 15, "precipi": 40, "precipi_is_zero": false, "is_forecast": true}, {"mintempi": 46, "dayname": "Tue", "maxtempi": 54, "daynum": 16, "precipi": 60, "precipi_is_zero": false, "is_forecast": true}, {"mintempi": 47, "dayname": "Wed", "maxtempi": 57, "daynum": 17, "precipi": 60, "precipi_is_zero": false, "is_forecast": true}, {"mintempi": 46, "dayname": "Thu", "maxtempi": 53, "daynum": 18, "precipi": 60, "precipi_is_zero": false, "is_forecast": true}, {"mintempi": 44, "dayname": "Fri", "maxtempi": 52, "daynum": 19, "precipi": 60, "precipi_is_zero": false, "is_forecast": true}, {"mintempi": 43, "dayname": "Sat", "maxtempi": 53, "daynum": 20, "precipi": 20, "precipi_is_zero": false, "is_forecast": true}, {"mintempi": 45, "dayname": "Sun", "maxtempi": 58, "daynum": 21, "precipi": 60, "precipi_is_zero": false, "is_forecast": true}], "total_rain": 2.23}