{"response": {"termsofService": "http://www.wunderground.com/weather/api/d/terms.html", "version": "0.1", "features": {"history": 1}}, "history": {"date": {"mday": "11", "hour": "12", "min": "00", "mon": "09", "pretty": "September 11, 2013", "year": "2013", "tzname": "America/Los_Angeles"}, "utcdate": {"mday": "11", "hour": "19", "min": "00", "mon": "09", "pretty": "September 11, 2013", "year": "2013", "tzname": "UTC"}, "observations": [{"heatindexm": "-9999", "windchillm": "-999", "wdire": "SSE", "wdird": "150", "windchilli": "-999", "hail": "0", "heatindexi": "-9999", "precipi": "-9999.00", "thunder": "0", "pressurei": "29.88", "snow": "0", "pressurem": "1011.7", "fog": "0", "icon": "partlycloudy", "precipm": "-9999.00", "conds": "Scattered Clouds", "tornado": "0", "hum": "83", "tempi": "61.0", "tempm": "16.1", "dewptm": "13.3", "rain": "0", "dewpti": "55.9", "date": {"mday": "11", "hour": "00", "min": "56", "mon": "09", "pretty": "12:56 AM PDT on September 11, 2013", "year": "2013", "tzname": "America/Los_Angeles"}, "visi": "10.0", "vism": "16.1", "utcdate": {"mday": "11", "hour": "07", "min": "56", "mon": "09", "pretty": "7:56 AM GMT on September 11, 2013", "year": "2013", "tzname": "UTC"}, "wgusti": "-9999.0", "metar": "METAR KUKI 110756Z AUTO 15009KT 10SM SCT014 16/13 A2990 RMK AO2 SLP117 T01610133 403220139", "wgustm": "-9999.0", "wspdi": "10.4", "wspdm": "16.7"}, {"heatindexm": "-9999", "windchillm": "-999", "wdire": "SSE", "wdird": "150", "windchilli": "-999", "hail": "0", "heatindexi": "-9999", "precipi": "-9999.00", "thunder": "0", "pressurei": "29.90", "snow": "0", "pressurem": "1012.4", "fog": "0", "icon": "mostlycloudy", "precipm": "-9999.00", "conds": "Mostly Cloudy", "tornado": "0", "hum": "82", "tempi": "60.8", "tempm": "16.0", "dewptm": "13.0", "rain": "0", "dewpti": "55.4", "date": {"mday": "11", "hour": "01", "min": "54", "mon": "09", "pretty": "1:54 AM PDT on September 11, 2013", "year": "2013", "tzname": "America/Los_Angeles"}, "visi": "10.0", "vism": "16.1", "utcdate": {"mday": "11", "hour": "08", "min": "54", "mon": "09", "pretty": "8:54 AM GMT on September 11, 2013", "year": "2013", "tzname": "UTC"}, "wgusti": "-9999.0", "metar": "SPECI KUKI 110854Z AUTO 15006KT 10SM BKN014 16/13 A2990 RMK AO2", "wgustm": "-9999.0", "wspdi": "6.9", "wspdm": "11.1"}, {"heatindexm": "-9999", "windchillm": "-999", "wdire": "SSE", "wdird": "150", "windchilli": "-999", "hail": "0", "heatindexi": "-9999", "precipi": "-9999.00", "thunder": "0", "pressurei": "29.88", "snow": "0", "pressurem": "1011.8", "fog": "0", "icon": "mostlycloudy", "precipm": "-9999.00", "conds": "Mostly Cloudy", "tornado": "0", "hum": "83", "tempi": "61.0", "tempm": "16.1", "dewptm": "13.3", "rain": "0", "dewpti": "55.9", "date": {"mday": "11", "hour": "01", "min": "56", "mon": "09", "pretty": "1:56 AM PDT on September 11, 2013", "year": "2013", "tzname": "America/Los_Angeles"}, "visi": "10.0", "vism": "16.1", "utcdate": {"mday": "11", "hour": "08", "min": "56", "mon": "09", "pretty": "8:56 AM GMT on September 11, 2013", "year": "2013", "tzname": "UTC"}, "wgusti": "-9999.0", "metar": "METAR KUKI 110856Z AUTO 15007KT 10SM BKN014 16/13 A2991 RMK AO2 SLP118 T01610133 51005", "wgustm": "-9999.0", "wspdi": "8.1", "wspdm": "13.0"}, {"heatindexm": "-9999", "windchillm": "-999", "wdire": "South", "wdird": "170", "windchilli": "-999", "hail": "0", "heatindexi": "-9999", "precipi": "-9999.00", "thunder": "0", "pressurei": "29.89", "snow": "0", "pressurem": "1012.1", "fog": "0", "icon": "cloudy", "precipm": "-9999.00", "conds": "Overcast", "tornado": "0", "hum": "83", "tempi": "61.0", "tempm": "16.1", "dewptm": "13.3", "rain": "0", "dewpti": "55.9", "date": {"mday": "11", "hour": "02", "min": "56", "mon": "09", "pretty": "2:56 AM PDT on September 11, 2013", "year": "2013", "tzname": "America/Los_Angeles"}, "visi": "10.0", "vism": "16.1", "utcdate": {"mday": "11", "hour": "09", "min": "56", "mon": "09", "pretty": "9:56 AM GMT on September 11, 2013", "year": "2013", "tzname": "UTC"}, "wgusti": "-9999.0", "metar": "METAR KUKI 110956Z AUTO 17003KT 10SM OVC012 16/13 A2991 RMK AO2 SLP121 T01610133", "wgustm": "-9999.0", "wspdi": "3.5", "wspdm": "5.6"}, {"heatindexm": "-9999", "windchillm": "-999", "wdire": "South", "wdird": "170", "windchilli": "-999", "hail": "0", "heatindexi": "-9999", "precipi": "-9999.00", "thunder": "0", "pressurei": "29.90", "snow": "0", "pressurem": "1012.3", "fog": "0", "icon": "cloudy", "precipm": "-9999.00", "conds": "Overcast", "tornado": "0", "hum": "81", "tempi": "61.0", "tempm": "16.1", "dewptm": "12.8", "rain": "0", "dewpti": "55.0", "date": {"mday": "11", "hour": "03", "min": "56", "mon": "09", "pretty": "3:56 AM PDT on September 11, 2013", "year": "2013", "tzname": "America/Los_Angeles"}, "visi": "10.0", "vism": "16.1", "utcdate": {"mday": "11", "hour": "10", "min": "56", "mon": "09", "pretty": "10:56 AM GMT on September 11, 2013", "year": "2013", "tzname": "UTC"}, "wgusti": "-9999.0", "metar": "METAR KUKI 111056Z AUTO 17003KT 10SM OVC012 16/13 A2992 RMK AO2 SLP123 T01610128", "wgustm": "-9999.0", "wspdi": "3.5", "wspdm": "5.6"}, {"heatindexm": "-9999", "windchillm": "-999", "wdire": "SSE", "wdird": "150", "windchilli": "-999", "hail": "0", "heatindexi": "-9999", "precipi": "-9999.00", "thunder": "0", "pressurei": "29.90", "snow": "0", "pressurem": "1012.5", "fog": "0", "icon": "cloudy", "precipm": "-9999.00", "conds": "Overcast", "tornado": "0", "hum": "81", "tempi": "61.0", "tempm": "16.1", "dewptm": "12.8", "rain": "0", "dewpti": "55.0", "date": {"mday": "11", "hour": "04", "min": "56", "mon": "09", "pretty": "4:56 AM PDT on September 11, 2013", "year": "2013", "tzname": "America/Los_Angeles"}, "visi": "10.0", "vism": "16.1", "utcdate": {"mday": "11", "hour": "11", "min": "56", "mon": "09", "pretty": "11:56 AM GMT on September 11, 2013", "year": "2013", "tzname": "UTC"}, "wgusti": "-9999.0", "metar": "METAR KUKI 111156Z AUTO 15005KT 10SM OVC012 16/13 A2992 RMK AO2 SLP125 T01610128 10167 20156 53006", "wgustm": "-9999.0", "wspdi": "5.8", "wspdm": "9.3"}, {"heatindexm": "-9999", "windchillm": "-999", "wdire": "South", "wdird": "170", "windchilli": "-999", "hail": "0", "heatindexi": "-9999", "precipi": "-9999.00", "thunder": "0", "pressurei": "29.92", "snow": "0", "pressurem": "1013.1", "fog": "0", "icon": "cloudy", "precipm": "-9999.00", "conds": "Overcast", "tornado": "0", "hum": "81", "tempi": "61.0", "tempm": "16.1", "dewptm": "12.8", "rain": "0", "dewpti": "55.0", "date": {"mday": "11", "hour": "05", "min": "56", "mon": "09", "pretty": "5:56 AM PDT on September 11, 2013", "year": "2013", "tzname": "America/Los_Angeles"}, "visi": "10.0", "vism": "16.1", "utcdate": {"mday": "11", "hour": "12", "min": "56", "mon": "09", "pretty": "12:56 PM GMT on September 11, 2013", "year": "2013", "tzname": "UTC"}, "wgusti": "-9999.0", "metar": "METAR KUKI 111256Z AUTO 17003KT 10SM OVC012 16/13 A2994 RMK AO2 SLP131 T01610128", "wgustm": "-9999.0", "wspdi": "3.5", "wspdm": "5.6"}, {"heatindexm": "-9999", "windchillm": "-999", "wdire": "South", "wdird": "170", "windchilli": "-999", "hail": "0", "heatindexi": "-9999", "precipi": "-9999.00", "thunder": "0", "pressurei": "29.94", "snow": "0", "pressurem": "1013.7", "fog": "0", "icon": "cloudy", "precipm": "-9999.00", "conds": "Overcast", "tornado": "0", "hum": "81", "tempi": "61.0", "tempm": "16.1", "dewptm": "12.8", "rain": "0", "dewpti": "55.0", "date": {"mday": "11", "hour": "06", "min": "56", "mon": "09", "pretty": "6:56 AM PDT on September 11, 2013", "year": "2013", "tzname": "America/Los_Angeles"}, "visi": "10.0", "vism": "16.1", "utcdate": {"mday": "11", "hour": "13", "min": "56", "mon": "09", "pretty": "1:56 PM GMT on September 11, 2013", "year": "2013", "tzname": "UTC"}, "wgusti": "-9999.0", "metar": "METAR KUKI 111356Z AUTO 17004KT 10SM OVC012 16/13 A2996 RMK AO2 SLP137 T01610128", "wgustm": "-9999.0", "wspdi": "4.6", "wspdm": "7.4"}, {"heatindexm": "-9999", "windchillm": "-999", "wdire": "South", "wdird": "170", "windchilli": "-999", "hail": "0", "heatindexi": "-9999", "precipi": "-9999.00", "thunder": "0", "pressurei": "29.95", "snow": "0", "pressurem": "1014.1", "fog": "0", "icon": "cloudy", "precipm": "-9999.00", "conds": "Overcast", "tornado": "0", "hum": "81", "tempi": "61.0", "tempm": "16.1", "dewptm": "12.8", "rain": "0", "dewpti": "55.0", "date": {"mday": "11", "hour": "07", "min": "56", "mon": "09", "pretty": "7:56 AM PDT on September 11, 2013", "year": "2013", "tzname": "America/Los_Angeles"}, "visi": "10.0", "vism": "16.1", "utcdate": {"mday": "11", "hour": "14", "min": "56", "mon": "09", "pretty": "2:56 PM GMT on September 11, 2013", "year": "2013", "tzname": "UTC"}, "wgusti": "-9999.0", "metar": "METAR KUKI 111456Z AUTO 17004KT 10SM OVC012 16/13 A2997 RMK AO2 SLP141 T01610128 51015", "wgustm": "-9999.0", "wspdi": "4.6", "wspdm": "7.4"}, {"heatindexm": "-9999", "windchillm": "-999", "wdire": "SE", "wdird": "140", "windchilli": "-999", "hail": "0", "heatindexi": "-9999", "precipi": "-9999.00", "thunder": "0", "pressurei": "29.96", "snow": "0", "pressurem": "1014.4", "fog": "0", "icon": "cloudy", "precipm": "-9999.00", "conds": "Overcast", "tornado": "0", "hum": "78", "tempi": "63.0", "tempm": "17.2", "dewptm": "13.3", "rain": "0", "dewpti": "55.9", "date": {"mday": "11", "hour": "08", "min": "56", "mon": "09", "pretty": "8:56 AM PDT on September 11, 2013", "year": "2013", "tzname": "America/Los_Angeles"}, "visi": "10.0", "vism": "16.1", "utcdate": {"mday": "11", "hour": "15", "min": "56", "mon": "09", "pretty": "3:56 PM GMT on September 11, 2013", "year": "2013", "tzname": "UTC"}, "wgusti": "-9999.0", "metar": "METAR KUKI 111556Z AUTO 14007KT 10SM OVC012 17/13 A2998 RMK AO2 SLP144 T01720133", "wgustm": "-9999.0", "wspdi": "8.1", "wspdm": "13.0"}, {"heatindexm": "-9999", "windchillm": "-999", "wdire": "ESE", "wdird": "120", "windchilli": "-999", "hail": "0", "heatindexi": "-9999", "precipi": "-9999.00", "thunder": "0", "pressurei": "29.96", "snow": "0", "pressurem": "1014.6", "fog": "0", "icon": "cloudy", "precipm": "-9999.00", "conds": "Overcast", "tornado": "0", "hum": "70", "tempi": "66.0", "tempm": "18.9", "dewptm": "13.3", "rain": "0", "dewpti": "55.9", "date": {"mday": "11", "hour": "09", "min": "56", "mon": "09", "pretty": "9:56 AM PDT on September 11, 2013", "year": "2013", "tzname": "America/Los_Angeles"}, "visi": "10.0", "vism": "16.1", "utcdate": {"mday": "11", "hour": "16", "min": "56", "mon": "09", "pretty": "4:56 PM GMT on September 11, 2013", "year": "2013", "tzname": "UTC"}, "wgusti": "-9999.0", "metar": "METAR KUKI 111656Z AUTO 12007KT 10SM OVC016 19/13 A2998 RMK AO2 SLP146 T01890133", "wgustm": "-9999.0", "wspdi": "8.1", "wspdm": "13.0"}, {"heatindexm": "-9999", "windchillm": "-999", "wdire": "ESE", "wdird": "120", "windchilli": "-999", "hail": "0", "heatindexi": "-9999", "precipi": "-9999.00", "thunder": "0", "pressurei": "29.99", "snow": "0", "pressurem": "1015.5", "fog": "0", "icon": "partlycloudy", "precipm": "-9999.00", "conds": "Scattered Clouds", "tornado": "0", "hum": "68", "tempi": "66.2", "tempm": "19.0", "dewptm": "13.0", "rain": "0", "dewpti": "55.4", "date": {"mday": "11", "hour": "10", "min": "12", "mon": "09", "pretty": "10:12 AM PDT on September 11, 2013", "year": "2013", "tzname": "America/Los_Angeles"}, "visi": "10.0", "vism": "16.1", "utcdate": {"mday": "11", "hour": "17", "min": "12", "mon": "09", "pretty": "5:12 PM GMT on September 11, 2013", "year": "2013", "tzname": "UTC"}, "wgusti": "-9999.0", "metar": "SPECI KUKI 111712Z AUTO 12008KT 10SM SCT016 19/13 A2999 RMK AO2", "wgustm": "-9999.0", "wspdi": "9.2", "wspdm": "14.8"}, {"heatindexm": "-9999", "windchillm": "-999", "wdire": "SE", "wdird": "140", "windchilli": "-999", "hail": "0", "heatindexi": "-9999", "precipi": "-9999.00", "thunder": "0", "pressurei": "29.96", "snow": "0", "pressurem": "1014.6", "fog": "0", "icon": "clear", "precipm": "-9999.00", "conds": "Clear", "tornado": "0", "hum": "65", "tempi": "68.0", "tempm": "20.0", "dewptm": "13.3", "rain": "0", "dewpti": "55.9", "date": {"mday": "11", "hour": "10", "min": "56", "mon": "09", "pretty": "10:56 AM PDT on September 11, 2013", "year": "2013", "tzname": "America/Los_Angeles"}, "visi": "10.0", "vism": "16.1", "utcdate": {"mday": "11", "hour": "17", "min": "56", "mon": "09", "pretty": "5:56 PM GMT on September 11, 2013", "year": "2013", "tzname": "UTC"}, "wgusti": "-9999.0", "metar": "METAR KUKI 111756Z AUTO 14009KT 110V170 10SM CLR 20/13 A2998 RMK AO2 SLP146 T02000133 10206 20161 50004", "wgustm": "-9999.0", "wspdi": "10.4", "wspdm": "16.7"}, {"heatindexm": "-9999", "windchillm": "-999", "wdire": "SE", "wdird": "140", "windchilli": "-999", "hail": "0", "heatindexi": "-9999", "precipi": "-9999.00", "thunder": "0", "pressurei": "29.96", "snow": "0", "pressurem": "1014.5", "fog": "0", "icon": "clear", "precipm": "-9999.00", "conds": "Clear", "tornado": "0", "hum": "59", "tempi": "71.1", "tempm": "21.7", "dewptm": "13.3", "rain": "0", "dewpti": "55.9", "date": {"mday": "11", "hour": "11", "min": "56", "mon": "09", "pretty": "11:56 AM PDT on September 11, 2013", "year": "2013", "tzname": "America/Los_Angeles"}, "visi": "10.0", "vism": "16.1", "utcdate": {"mday": "11", "hour": "18", "min": "56", "mon": "09", "pretty": "6:56 PM GMT on September 11, 2013", "year": "2013", "tzname": "UTC"}, "wgusti": "-9999.0", "metar": "METAR KUKI 111856Z AUTO 14010KT 10SM CLR 22/13 A2998 RMK AO2 SLP145 T02170133", "wgustm": "-9999.0", "wspdi": "11.5", "wspdm": "18.5"}, {"heatindexm": "-9999", "windchillm": "-999", "wdire": "SE", "wdird": "130", "windchilli": "-999", "hail": "0", "heatindexi": "-9999", "precipi": "-9999.00", "thunder": "0", "pressurei": "29.95", "snow": "0", "pressurem": "1014.2", "fog": "0", "icon": "clear", "precipm": "-9999.00", "conds": "Clear", "tornado": "0", "hum": "57", "tempi": "73.0", "tempm": "22.8", "dewptm": "13.9", "rain": "0", "dewpti": "57.0", "date": {"mday": "11", "hour": "12", "min": "56", "mon": "09", "pretty": "12:56 PM PDT on September 11, 2013", "year": "2013", "tzname": "America/Los_Angeles"}, "visi": "10.0", "vism": "16.1", "utcdate": {"mday": "11", "hour": "19", "min": "56", "mon": "09", "pretty": "7:56 PM GMT on September 11, 2013", "year": "2013", "tzname": "UTC"}, "wgusti": "20.7", "metar": "METAR KUKI 111956Z AUTO 13013G18KT 10SM CLR 23/14 A2997 RMK AO2 SLP142 T02280139", "wgustm": "33.3", "wspdi": "15.0", "wspdm": "24.1"}, {"heatindexm": "-9999", "windchillm": "-999", "wdire": "SSE", "wdird": "160", "windchilli": "-999", "hail": "0", "heatindexi": "-9999", "precipi": "-9999.00", "thunder": "0", "pressurei": "29.94", "snow": "0", "pressurem": "1013.7", "fog": "0", "icon": "clear", "precipm": "-9999.00", "conds": "Clear", "tornado": "0", "hum": "52", "tempi": "75.9", "tempm": "24.4", "dewptm": "13.9", "rain": "0", "dewpti": "57.0", "date": {"mday": "11", "hour": "13", "min": "56", "mon": "09", "pretty": "1:56 PM PDT on September 11, 2013", "year": "2013", "tzname": "America/Los_Angeles"}, "visi": "10.0", "vism": "16.1", "utcdate": {"mday": "11", "hour": "20", "min": "56", "mon": "09", "pretty": "8:56 PM GMT on September 11, 2013", "year": "2013", "tzname": "UTC"}, "wgusti": "-9999.0", "metar": "METAR KUKI 112056Z AUTO 16010KT 10SM CLR 24/14 A2995 RMK AO2 SLP137 T02440139 58009", "wgustm": "-9999.0", "wspdi": "11.5", "wspdm": "18.5"}, {"heatindexm": "-9999", "windchillm": "-999", "wdire": "SSE", "wdird": "150", "windchilli": "-999", "hail": "0", "heatindexi": "-9999", "precipi": "-9999.00", "thunder": "0", "pressurei": "29.91", "snow": "0", "pressurem": "1012.9", "fog": "0", "icon": "clear", "precipm": "-9999.00", "conds": "Clear", "tornado": "0", "hum": "48", "tempi": "79.0", "tempm": "26.1", "dewptm": "14.4", "rain": "0", "dewpti": "57.9", "date": {"mday": "11", "hour": "14", "min": "56", "mon": "09", "pretty": "2:56 PM PDT on September 11, 2013", "year": "2013", "tzname": "America/Los_Angeles"}, "visi": "10.0", "vism": "16.1", "utcdate": {"mday": "11", "hour": "21", "min": "56", "mon": "09", "pretty": "9:56 PM GMT on September 11, 2013", "year": "2013", "tzname": "UTC"}, "wgusti": "18.4", "metar": "METAR KUKI 112156Z AUTO 15010G16KT 10SM CLR 26/14 A2993 RMK AO2 SLP129 T02610144", "wgustm": "29.6", "wspdi": "11.5", "wspdm": "18.5"}, {"heatindexm": "-9999", "windchillm": "-999", "wdire": "SSE", "wdird": "150", "windchilli": "-999", "hail": "0", "heatindexi": "-9999", "precipi": "-9999.00", "thunder": "0", "pressurei": "29.90", "snow": "0", "pressurem": "1012.5", "fog": "0", "icon": "clear", "precipm": "-9999.00", "conds": "Clear", "tornado": "0", "hum": "48", "tempi": "79.0", "tempm": "26.1", "dewptm": "14.4", "rain": "0", "dewpti": "57.9", "date": {"mday": "11", "hour": "15", "min": "56", "mon": "09", "pretty": "3:56 PM PDT on September 11, 2013", "year": "2013", "tzname": "America/Los_Angeles"}, "visi": "10.0", "vism": "16.1", "utcdate": {"mday": "11", "hour": "22", "min": "56", "mon": "09", "pretty": "10:56 PM GMT on September 11, 2013", "year": "2013", "tzname": "UTC"}, "wgusti": "-9999.0", "metar": "METAR KUKI 112256Z AUTO 15011KT 10SM CLR 26/14 A2992 RMK AO2 SLP125 T02610144", "wgustm": "-9999.0", "wspdi": "12.7", "wspdm": "20.4"}, {"heatindexm": "-9999", "windchillm": "-999", "wdire": "SSE", "wdird": "150", "windchilli": "-999", "hail": "0", "heatindexi": "-9999", "precipi": "-9999.00", "thunder": "0", "pressurei": "29.89", "snow": "0", "pressurem": "1012.2", "fog": "0", "icon": "clear", "precipm": "-9999.00", "conds": "Clear", "tornado": "0", "hum": "48", "tempi": "79.0", "tempm": "26.1", "dewptm": "14.4", "rain": "0", "dewpti": "57.9", "date": {"mday": "11", "hour": "16", "min": "56", "mon": "09", "pretty": "4:56 PM PDT on September 11, 2013", "year": "2013", "tzname": "America/Los_Angeles"}, "visi": "10.0", "vism": "16.1", "utcdate": {"mday": "11", "hour": "23", "min": "56", "mon": "09", "pretty": "11:56 PM GMT on September 11, 2013", "year": "2013", "tzname": "UTC"}, "wgusti": "-9999.0", "metar": "METAR KUKI 112356Z AUTO 15009KT 10SM CLR 26/14 A2991 RMK AO2 SLP122 T02610144 10272 20200 56014", "wgustm": "-9999.0", "wspdi": "10.4", "wspdm": "16.7"}, {"heatindexm": "-9999", "windchillm": "-999", "wdire": "SSE", "wdird": "160", "windchilli": "-999", "hail": "0", "heatindexi": "-9999", "precipi": "-9999.00", "thunder": "0", "pressurei": "29.89", "snow": "0", "pressurem": "1012.2", "fog": "0", "icon": "clear", "precipm": "-9999.00", "conds": "Clear", "tornado": "0", "hum": "48", "tempi": "79.0", "tempm": "26.1", "dewptm": "14.4", "rain": "0", "dewpti": "57.9", "date": {"mday": "11", "hour": "17", "min": "56", "mon": "09", "pretty": "5:56 PM PDT on September 11, 2013", "year": "2013", "tzname": "America/Los_Angeles"}, "visi": "10.0", "vism": "16.1", "utcdate": {"mday": "12", "hour": "00", "min": "56", "mon": "09", "pretty": "12:56 AM GMT on September 12, 2013", "year": "2013", "tzname": "UTC"}, "wgusti": "-9999.0", "metar": "METAR KUKI 120056Z AUTO 16005KT 10SM CLR 26/14 A2991 RMK AO2 SLP122 T02610144", "wgustm": "-9999.0", "wspdi": "5.8", "wspdm": "9.3"}, {"heatindexm": "-9999", "windchillm": "-999", "wdire": "SSE", "wdird": "150", "windchilli": "-999", "hail": "0", "heatindexi": "-9999", "precipi": "-9999.00", "thunder": "0", "pressurei": "29.90", "snow": "0", "pressurem": "1012.4", "fog": "0", "icon": "clear", "precipm": "-9999.00", "conds": "Clear", "tornado": "0", "hum": "55", "tempi": "75.0", "tempm": "23.9", "dewptm": "14.4", "rain": "0", "dewpti": "57.9", "date": {"mday": "11", "hour": "18", "min": "56", "mon": "09", "pretty": "6:56 PM PDT on September 11, 2013", "year": "2013", "tzname": "America/Los_Angeles"}, "visi": "10.0", "vism": "16.1", "utcdate": {"mday": "12", "hour": "01", "min": "56", "mon": "09", "pretty": "1:56 AM GMT on September 12, 2013", "year": "2013", "tzname": "UTC"}, "wgusti": "-9999.0", "metar": "METAR KUKI 120156Z AUTO 15005KT 10SM CLR 24/14 A2992 RMK AO2 SLP124 T02390144", "wgustm": "-9999.0", "wspdi": "5.8", "wspdm": "9.3"}, {"heatindexm": "-9999", "windchillm": "-999", "wdire": "North", "wdird": "0", "windchilli": "-999", "hail": "0", "heatindexi": "-9999", "precipi": "-9999.00", "thunder": "0", "pressurei": "29.91", "snow": "0", "pressurem": "1012.9", "fog": "0", "icon": "clear", "precipm": "-9999.00", "conds": "Clear", "tornado": "0", "hum": "61", "tempi": "72.0", "tempm": "22.2", "dewptm": "14.4", "rain": "0", "dewpti": "57.9", "date": {"mday": "11", "hour": "19", "min": "56", "mon": "09", "pretty": "7:56 PM PDT on September 11, 2013", "year": "2013", "tzname": "America/Los_Angeles"}, "visi": "10.0", "vism": "16.1", "utcdate": {"mday": "12", "hour": "02", "min": "56", "mon": "09", "pretty": "2:56 AM GMT on September 12, 2013", "year": "2013", "tzname": "UTC"}, "wgusti": "-9999.0", "metar": "METAR KUKI 120256Z AUTO 00000KT 10SM CLR 22/14 A2993 RMK AO2 SLP129 T02220144 53006", "wgustm": "-9999.0", "wspdi": "0.0", "wspdm": "0.0"}, {"heatindexm": "-9999", "windchillm": "-999", "wdire": "South", "wdird": "180", "windchilli": "-999", "hail": "0", "heatindexi": "-9999", "precipi": "-9999.00", "thunder": "0", "pressurei": "29.93", "snow": "0", "pressurem": "1013.4", "fog": "0", "icon": "clear", "precipm": "-9999.00", "conds": "Clear", "tornado": "0", "hum": "68", "tempi": "69.1", "tempm": "20.6", "dewptm": "14.4", "rain": "0", "dewpti": "57.9", "date": {"mday": "11", "hour": "20", "min": "56", "mon": "09", "pretty": "8:56 PM PDT on September 11, 2013", "year": "2013", "tzname": "America/Los_Angeles"}, "visi": "10.0", "vism": "16.1", "utcdate": {"mday": "12", "hour": "03", "min": "56", "mon": "09", "pretty": "3:56 AM GMT on September 12, 2013", "year": "2013", "tzname": "UTC"}, "wgusti": "-9999.0", "metar": "METAR KUKI 120356Z AUTO 18005KT 10SM CLR 21/14 A2995 RMK AO2 SLP134 T02060144", "wgustm": "-9999.0", "wspdi": "5.8", "wspdm": "9.3"}, {"heatindexm": "-9999", "windchillm": "-999", "wdire": "South", "wdird": "190", "windchilli": "-999", "hail": "0", "heatindexi": "-9999", "precipi": "-9999.00", "thunder": "0", "pressurei": "29.94", "snow": "0", "pressurem": "1013.7", "fog": "0", "icon": "clear", "precipm": "-9999.00", "conds": "Clear", "tornado": "0", "hum": "73", "tempi": "66.0", "tempm": "18.9", "dewptm": "13.9", "rain": "0", "dewpti": "57.0", "date": {"mday": "11", "hour": "21", "min": "56", "mon": "09", "pretty": "9:56 PM PDT on September 11, 2013", "year": "2013", "tzname": "America/Los_Angeles"}, "visi": "10.0", "vism": "16.1", "utcdate": {"mday": "12", "hour": "04", "min": "56", "mon": "09", "pretty": "4:56 AM GMT on September 12, 2013", "year": "2013", "tzname": "UTC"}, "wgusti": "-9999.0", "metar": "METAR KUKI 120456Z AUTO 19006KT 10SM CLR 19/14 A2996 RMK AO2 SLP137 T01890139", "wgustm": "-9999.0", "wspdi": "6.9", "wspdm": "11.1"}, {"heatindexm": "-9999", "windchillm": "-999", "wdire": "South", "wdird": "190", "windchilli": "-999", "hail": "0", "heatindexi": "-9999", "precipi": "-9999.00", "thunder": "0", "pressurei": "29.95", "snow": "0", "pressurem": "1014.0", "fog": "0", "icon": "clear", "precipm": "-9999.00", "conds": "Clear", "tornado": "0", "hum": "78", "tempi": "64.0", "tempm": "17.8", "dewptm": "13.9", "rain": "0", "dewpti": "57.0", "date": {"mday": "11", "hour": "22", "min": "56", "mon": "09", "pretty": "10:56 PM PDT on September 11, 2013", "year": "2013", "tzname": "America/Los_Angeles"}, "visi": "10.0", "vism": "16.1", "utcdate": {"mday": "12", "hour": "05", "min": "56", "mon": "09", "pretty": "5:56 AM GMT on September 12, 2013", "year": "2013", "tzname": "UTC"}, "wgusti": "-9999.0", "metar": "METAR KUKI 120556Z AUTO 19005KT 10SM CLR 18/14 A2996 RMK AO2 SLP140 T01780139 10267 20178 51011", "wgustm": "-9999.0", "wspdi": "5.8", "wspdm": "9.3"}, {"heatindexm": "-9999", "windchillm": "-999", "wdire": "South", "wdird": "170", "windchilli": "-999", "hail": "0", "heatindexi": "-9999", "precipi": "-9999.00", "thunder": "0", "pressurei": "29.96", "snow": "0", "pressurem": "1014.3", "fog": "0", "icon": "clear", "precipm": "-9999.00", "conds": "Clear", "tornado": "0", "hum": "81", "tempi": "63.0", "tempm": "17.2", "dewptm": "13.9", "rain": "0", "dewpti": "57.0", "date": {"mday": "11", "hour": "23", "min": "56", "mon": "09", "pretty": "11:56 PM PDT on September 11, 2013", "year": "2013", "tzname": "America/Los_Angeles"}, "visi": "10.0", "vism": "16.1", "utcdate": {"mday": "12", "hour": "06", "min": "56", "mon": "09", "pretty": "6:56 AM GMT on September 12, 2013", "year": "2013", "tzname": "UTC"}, "wgusti": "-9999.0", "metar": "METAR KUKI 120656Z AUTO 17004KT 10SM CLR 17/14 A2997 RMK AO2 SLP143 T01720139", "wgustm": "-9999.0", "wspdi": "4.6", "wspdm": "7.4"}], "dailysummary": [{"maxpressurem": "1015", "maxdewptm": "14", "maxpressurei": "29.99", "maxdewpti": "58", "since1julheatingdegreedaysnormal": "", "heatingdegreedaysnormal": "", "since1sepcoolingdegreedaysnormal": "", "hail": "0", "since1julsnowfallm": "0.00", "date": {"mday": "11", "hour": "12", "min": "00", "mon": "09", "pretty": "12:00 PM PDT on September 11, 2013", "year": "2013", "tzname": "America/Los_Angeles"}, "since1julheatingdegreedays": "", "maxvisi": "10", "since1sepheatingdegreedaysnormal": "", "heatingdegreedays": "0", "mindewptm": "13", "since1sepheatingdegreedays": "", "maxwspdm": "26", "since1julsnowfalli": "0.00", "since1sepcoolingdegreedays": "", "snow": "0", "meanvism": "16", "meandewptm": "13", "snowdepthm": "", "meanvisi": "10", "fog": "0", "snowdepthi": "", "minvism": "16", "since1jancoolingdegreedays": "", "minvisi": "10", "coolingdegreedaysnormal": "", "gdegreedays": "20", "maxwspdi": "16", "meanwindspdi": "8", "meanpressurei": "29.93", "monthtodateheatingdegreedaysnormal": "", "meanwindspdm": "13", "meanpressurem": "1013", "tornado": "0", "mindewpti": "55", "mintempi": "60", "meandewpti": "56", "rain": "0", "mintempm": "16", "minhumidity": "48", "precipsource": "", "minwspdi": "0", "meanwdird": "156", "meanwdire": "", "minwspdm": "0", "monthtodatesnowfalli": "0.00", "monthtodatecoolingdegreedaysnormal": "", "monthtodatesnowfallm": "0.00", "maxhumidity": "84", "coolingdegreedays": "4", "maxtempm": "27", "minpressurei": "29.88", "monthtodatecoolingdegreedays": "", "maxtempi": "81", "minpressurem": "1012", "humidity": "", "precipi": "0.00", "snowfalli": "0.00", "since1jancoolingdegreedaysnormal": "", "precipm": "0.00", "snowfallm": "0.00", "thunder": "0", "monthtodateheatingdegreedays": "", "meantempi": "71", "maxvism": "16", "meantempm": "22"}]}}